<?xml version='1.0' encoding='utf-8'?>
<!--
REFERENCES
- references/ISO-TS-13499/RED B/2020_06_17_ISO_TS13499_RED_B_1_6_2.pdf"
-->
<Channel_Codes version="1.6.2">
    <Codification>
        <Element name="Test Object">
            <Channel code="0???????????????" description="Undefined / other" version="1.0"/>
            <Channel code="1???????????????" description="Vehicle 1" remarks="also used to code several individual test objects in special setups" version="1.0"/>
            <Channel code="2???????????????" description="Vehicle 2" remarks="also used to code several individual test objects in special setups" version="1.0"/>
            <Channel code="3???????????????" description="Vehicle 3" remarks="also used to code several individual test objects in special setups" version="1.0"/>
            <Channel code="4???????????????" description="Vehicle 4" remarks="also used to code several individual test objects in special setups" version="1.0"/>
            <Channel code="5???????????????" description="Vehicle 5" remarks="also used to code several individual test objects in special setups" version="1.0"/>
            <Channel code="6???????????????" description="Vehicle 6" remarks="also used to code several individual test objects in special setups" version="1.0"/>
            <Channel code="7???????????????" description="Vehicle 7" remarks="also used to code several individual test objects in special setups" version="1.0"/>
            <Channel code="8???????????????" description="Vehicle 8" remarks="also used to code several individual test objects in special setups" version="1.0"/>
            <Channel code="9???????????????" description="Vehicle 9" remarks="also used to code several individual test objects in special setups" version="1.0"/>
            <Channel code="B???????????????" description="Fixed Barrier" version="1.0"/>
            <Channel code="C???????????????" description="Component" version="1.5"/>
            <Channel code="D???????????????" description="Dummy / Dummy Impactor" version="1.4"/>
            <Channel code="H???????????????" description="Linear Impactor" version="1.4"/>
            <Channel code="M???????????????" description="Mobile Barrier" version="1.0"/>
            <Channel code="P???????????????" description="Pendulum" version="1.0"/>
            <Channel code="S???????????????" description="Sled" version="1.0"/>
            <Channel code="T???????????????" description="Test Rig" version="1.4"/>
        </Element>
        <Element name="Position">
            <Channel code="?0??????????????" description="Undefined" version="1.0"/>
            <Channel code="?1??????????????" description="Front left" version="1.1"/>
            <Channel code="?2??????????????" description="Front middle" remarks="also used for motorcycle driver" version="1.1"/>
            <Channel code="?3??????????????" description="Front right" version="1.1"/>
            <Channel code="?4??????????????" description="Middle left / 2nd row left" version="1.1"/>
            <Channel code="?5??????????????" description="Middle middle / 2nd row middle" remarks="also used for motorcycle sozius" version="1.1"/>
            <Channel code="?6??????????????" description="Middle right / 2nd row right" version="1.1"/>
            <Channel code="?7??????????????" description="Rear left / 3rd row left" version="1.1"/>
            <Channel code="?8??????????????" description="Rear middle / 3rd row middle" version="1.1"/>
            <Channel code="?9??????????????" description="Rear right / 3rd row right" version="1.1"/>
            <Channel code="?A??????????????" description="Seat A" version="1.6.1"/>
            <Channel code="?B??????????????" description="Seat B" version="1.6.1"/>
            <Channel code="?C??????????????" description="Seat C" version="1.6.1"/>
            <Channel code="?D??????????????" description="Seat D" remarks="was Motorcycle driver in former revision -> use Position 2 instead" version="1.0"/>
            <Channel code="?E??????????????" description="Seat E" version="1.6.1"/>
            <Channel code="?F??????????????" description="Seat F" version="1.6.1"/>
            <Channel code="?G??????????????" description="Seat G" version="1.6.1"/>
            <Channel code="?H??????????????" description="Seat H" version="1.6.1"/>
            <Channel code="?I??????????????" description="Seat I" version="1.6.1"/>
            <Channel code="?J??????????????" description="Seat J" version="1.6.1"/>
            <Channel code="?K??????????????" description="Seat K" version="1.6.1"/>
            <Channel code="?L??????????????" description="Seat L" version="1.6.1"/>
            <Channel code="?M??????????????" description="Seat M" version="1.6.1"/>
            <Channel code="?N??????????????" description="Seat N" version="1.6.1"/>
            <Channel code="?O??????????????" description="Seat O" version="1.6.1"/>
            <Channel code="?P??????????????" description="Seat P" version="1.6.1"/>
            <Channel code="?Q??????????????" description="Seat Q" version="1.6.1"/>
            <Channel code="?R??????????????" description="Seat R" version="1.6.1"/>
            <Channel code="?S??????????????" description="Seat S" remarks="was Motorcycle sozius in former revision -> use Position 5 instead" version="1.0"/>
            <Channel code="?T??????????????" description="Seat T" version="1.6.1"/>
            <Channel code="?U??????????????" description="Seat U" version="1.6.1"/>
            <Channel code="?V??????????????" description="Seat V" version="1.6.1"/>
            <Channel code="?W??????????????" description="Seat W" version="1.6.1"/>
            <Channel code="?X??????????????" description="Seat X" version="1.6.1"/>
            <Channel code="?Y??????????????" description="Seat Y" version="1.6.1"/>
            <Channel code="?Z??????????????" description="Seat Z" version="1.6.1"/>
        </Element>
        <Element name="Main Location">
            <Category name="Human">
                <Channel code="??ACHI??????????" description="Achiles Tendon" remarks="intended for Human Models" version="1.6.2.p2"/>
                <Channel code="??ACRO??????????" description="Acromion" remarks="intended for Human Models" version="1.6.2.p2"/>
                <Channel code="??FIBU??????????" description="Fibula" remarks="intended for Human Models" version="1.6.2.p2"/>
                <Channel code="??LLEG??????????" description="Lower Leg" remarks="intended for Human Models" version="1.6.2.p2"/>
                <Channel code="??RADI??????????" description="Radius" remarks="intended for Human Models" version="1.6.2.p2"/>
                <Channel code="??SCAP??????????" description="Scapula" remarks="intended for Human Models" version="1.6.2.p2"/>
                <Channel code="??SKUL??????????" description="Skull" remarks="intended for Human Models" version="1.6.2.p2"/>
                <Channel code="??ULEG??????????" description="Upper Leg" remarks="intended for Human Models" version="1.6.2.p2"/>
                <Channel code="??ULNA??????????" description="Ulna" remarks="intended for Human Models" version="1.6.2.p2"/>
                <Channel code="??BRAI??????????" description="Brain" remarks="intended for Human Models" version="1.6.2.p2"/>
                <Channel code="??HUMS??????????" description="Humerus (upper arm bone)" remarks="intended for Human Models" version="1.0"/>
            </Category>
            <Category name="Dummy">
                <Channel code="??HEAD??????????" description="Head" version="1.0"/>
                <Channel code="??CESP??????????" description="Cervical Spine" version="1.0"/>
                <Channel code="??NECK??????????" description="Neck" version="1.0"/>
                <Channel code="??SHLD??????????" description="Shoulder" version="1.0"/>
                <Channel code="??CLAV??????????" description="Clavicle" version="1.0"/>
                <Channel code="??UPAR??????????" description="Upper Arm" version="1.1"/>
                <Channel code="??ELBJ??????????" description="Elbow Joint" version="1.0"/>
                <Channel code="??FOAR??????????" description="Forearm" version="1.1"/>
                <Channel code="??WRIS??????????" description="Wrist" version="1.0"/>
                <Channel code="??SHRI??????????" description="Shoulder Rib" version="1.0"/>
                <Channel code="??TRRI??????????" description="Thorax Rib" version="1.0"/>
                <Channel code="??RIBS??????????" description="Rib(s)" version="1.0"/>
                <Channel code="??CHRI??????????" description="Chest-Rib" version="1.0"/>
                <Channel code="??TRSP??????????" description="Thorax Rib to Spine" version="1.0"/>
                <Channel code="??SPIN??????????" description="Spine" version="1.0"/>
                <Channel code="??THSP??????????" description="Thoracic Spine" version="1.0"/>
                <Channel code="??BAPL??????????" description="Backplate" version="1.0"/>
                <Channel code="??MUSU??????????" description="Muscle Substitute" remarks="used for BR dummy" version="1.6"/>
                <Channel code="??CHST??????????" description="Chest" version="1.0"/>
                <Channel code="??STRN??????????" description="Sternum" version="1.0"/>
                <Channel code="??CHBA??????????" description="Chest Band" version="1.0"/>
                <Channel code="??ABRI??????????" description="Abdominal-Rib" version="1.0"/>
                <Channel code="??ABSP??????????" description="Abdominal-Spine" version="1.0"/>
                <Channel code="??ABDO??????????" description="Abdomen" version="1.0"/>
                <Channel code="??LUSP??????????" description="Lumbar Spine" version="1.0"/>
                <Channel code="??PELV??????????" description="Pelvis" version="1.0"/>
                <Channel code="??ACTB??????????" description="Acetabulum" version="1.0"/>
                <Channel code="??HPNT??????????" description="H-Point" version="1.2"/>
                <Channel code="??ILUM??????????" description="Ilium" version="1.0"/>
                <Channel code="??ILAC??????????" description="Iliac" version="1.0"/>
                <Channel code="??PUBC??????????" description="Pubic" version="1.0"/>
                <Channel code="??CROB??????????" description="Crotch Belt" version="1.0"/>
                <Channel code="??SACR??????????" description="Sacrum" version="1.0"/>
                <Channel code="??FEAC??????????" description="Femur to Acetabulum" version="1.0"/>
                <Channel code="??FEMR??????????" description="Femur" version="1.0"/>
                <Channel code="??KNEE??????????" description="Knee" version="1.0"/>
                <Channel code="??CLEV??????????" description="Clevis" version="1.0"/>
                <Channel code="??KNSL??????????" description="Knee Slider" version="1.0"/>
                <Channel code="??TIRA??????????" description="Tibia Ratio" version="1.1"/>
                <Channel code="??TIBI??????????" description="Tibia" version="1.0"/>
                <Channel code="??ANKL??????????" description="Ankle" version="1.0"/>
                <Channel code="??FOOT??????????" description="Foot" version="1.0"/>
                <Channel code="??HEEL??????????" description="Heel" version="1.0"/>
                <Channel code="??TOES??????????" description="Toe(s)" version="1.0"/>
                <Channel code="??DAMP??????????" description="Damper" version="1.0"/>
                <Channel code="??OCCU??????????" description="Occupant" remarks="intended for Video contour tracking" version="1.6.2.p1"/>
                <Channel code="??SUMA??????????" description="Submarining" version="1.0"/>
            </Category>
            <Category name="Vehicle">
                <Channel code="??ABSE??????????" description="Airbag Sensor" version="1.0"/>
                <Channel code="??AIRB??????????" description="Airbag" version="1.0"/>
                <Channel code="??APIL??????????" description="A-Pillar" version="1.0"/>
                <Channel code="??AXLE??????????" description="Axle" version="1.0"/>
                <Channel code="??BAFI??????????" description="Belt Anchor Fitting" version="1.5"/>
                <Channel code="??BATT??????????" description="Battery" version="1.0"/>
                <Channel code="??BCKL??????????" description="Buckle" version="1.0"/>
                <Channel code="??BLOK??????????" description="Belt Lock" version="1.0"/>
                <Channel code="??BLOP??????????" description="Belt Loop (reel return)" version="1.0"/>
                <Channel code="??BPIL??????????" description="B-Pillar" version="1.0"/>
                <Channel code="??BRBO??????????" description="Break Booster" version="1.6"/>
                <Channel code="??BUMP??????????" description="Bumper" version="1.0"/>
                <Channel code="??BUSY??????????" description="Bumper System" version="1.0"/>
                <Channel code="??CASH??????????" description="Cardan Shaft" version="1.6"/>
                <Channel code="??CCBE??????????" description="Cross Car Beam" version="1.0"/>
                <Channel code="??CEUN??????????" description="Central Unit" remarks="unit dedicated to Airbag, Restraint firing/activation" version="1.0"/>
                <Channel code="??CHAR??????????" description="Battery Charger" version="1.6.2"/>
                <Channel code="??CPIL??????????" description="C-Pillar" version="1.0"/>
                <Channel code="??CRAN??????????" description="Child Restraint Anchor" remarks="Figure missing (27.04.2007 os)" version="1.5"/>
                <Channel code="??CRME??????????" description="Crossmember" version="1.0"/>
                <Channel code="??CRSB??????????" description="Child Restraint Seatbelt" version="1.6"/>
                <Channel code="??CTAN??????????" description="Child Tether Anchorages" version="1.0"/>
                <Channel code="??CTUN??????????" description="Control Unit" remarks="all others beside CEUN" version="1.6.2"/>
                <Channel code="??DASB??????????" description="Dashboard" version="1.0"/>
                <Channel code="??DASH??????????" description="Dash Panel" version="1.0"/>
                <Channel code="??DIFF??????????" description="Differential" version="1.0"/>
                <Channel code="??DOOR??????????" description="Door" version="1.0"/>
                <Channel code="??DOPA??????????" description="Door Panel" version="1.6.2.p2"/>
                <Channel code="??DPIL??????????" description="D-Pillar" version="1.0"/>
                <Channel code="??ENGN??????????" description="Engine" version="1.0"/>
                <Channel code="??FEND??????????" description="Fender" version="1.0"/>
                <Channel code="??FORA??????????" description="Floor over Rear Axle" version="1.0"/>
                <Channel code="??FOWE??????????" description="Footwell" version="1.4"/>
                <Channel code="??FRAM??????????" description="Frame" remarks="often used for assembly frame in sled tests" version="1.0"/>
                <Channel code="??FREN??????????" description="Frontend" version="1.1"/>
                <Channel code="??FUL2??????????" description="Second Fuel Tank" version="1.6"/>
                <Channel code="??FULT??????????" description="Fuel Tank" version="1.0"/>
                <Channel code="??GEAR??????????" description="Gearbox" version="1.2"/>
                <Channel code="??GENR??????????" description="Generator" version="1.0"/>
                <Channel code="??HEPL??????????" description="Heel Plate" version="1.6"/>
                <Channel code="??HERE??????????" description="Head restraint" version="1.0"/>
                <Channel code="??HOOD??????????" description="Hood" version="1.0"/>
                <Channel code="??INSW??????????" description="Inertia Switch" version="1.0"/>
                <Channel code="??KNBO??????????" description="Knee Bolster" version="1.0"/>
                <Channel code="??LAMP??????????" description="Lamp" version="1.1"/>
                <Channel code="??LOCK??????????" description="Lock" version="1.0"/>
                <Channel code="??LOLI??????????" description="Load Limiter" version="1.5"/>
                <Channel code="??LOSY??????????" description="Lock System" version="1.0"/>
                <Channel code="??MSME??????????" description="Main Side Member" remarks="longitudinal beam close to the tunnel" version="1.6"/>
                <Channel code="??OILS??????????" description="Oil Sump" version="1.6"/>
                <Channel code="??PEAC??????????" description="Pedal Accelerator" version="1.0"/>
                <Channel code="??PEBR??????????" description="Pedal Brake" version="1.0"/>
                <Channel code="??PECL??????????" description="Pedal Clutch" version="1.0"/>
                <Channel code="??POCA??????????" description="Power Cable" version="1.6"/>
                <Channel code="??POEL??????????" description="Power Electronics" version="1.6"/>
                <Channel code="??PRET??????????" description="Pretensioner" version="1.0"/>
                <Channel code="??RACM??????????" description="Radiator Cross Member" version="1.6"/>
                <Channel code="??RETR??????????" description="Retractor" version="1.0"/>
                <Channel code="??ROFR??????????" description="Roof Frame" version="1.0"/>
                <Channel code="??ROOF??????????" description="Roof" version="1.0"/>
                <Channel code="??ROPS??????????" description="Rollover Protection System" version="1.6.2.p3"/>
                <Channel code="??RORA??????????" description="Roof Rack" version="1.0"/>
                <Channel code="??RVMB??????????" description="Rear View Mirror Base" version="1.6.2.p2"/>
                <Channel code="??RVMR??????????" description="Rear View Mirror" version="1.6.2.p2"/>
                <Channel code="??SBAD??????????" description="Seat Back Adjuster" version="1.6.1"/>
                <Channel code="??SBHA??????????" description="Seat Belt Height Adjuster" version="1.5"/>
                <Channel code="??SEAD??????????" description="Seat Adjuster" version="1.0"/>
                <Channel code="??SEAT??????????" description="Seat" version="1.0"/>
                <Channel code="??SEBA??????????" description="Seat Back" version="1.0"/>
                <Channel code="??SEBE??????????" description="Seat Belt" version="1.0"/>
                <Channel code="??SECM??????????" description="Seat Cross Member" version="1.6"/>
                <Channel code="??SEFR??????????" description="Seat Frame" version="1.0"/>
                <Channel code="??SEPN??????????" description="Seat Pan" version="1.3"/>
                <Channel code="??SERM??????????" description="Seat Rail Mount" version="1.6"/>
                <Channel code="??SETR??????????" description="Seat Track" version="1.0"/>
                <Channel code="??SILB??????????" description="Sill Beam" version="1.0"/>
                <Channel code="??SIME??????????" description="Side Member" remarks="longitudinal beam close to the outer side" version="1.0"/>
                <Channel code="??SLMB??????????" description="Slam Beam" version="1.2"/>
                <Channel code="??STAR??????????" description="Starter" version="1.0"/>
                <Channel code="??STBR??????????" description="Strut Brace" version="1.6.2"/>
                <Channel code="??STCM??????????" description="Steering Column Mount" version="1.0"/>
                <Channel code="??STCO??????????" description="Steering Column" version="1.0"/>
                <Channel code="??STCS??????????" description="Steering Column Suspension" version="1.0"/>
                <Channel code="??STEP??????????" description="Step" version="1.6"/>
                <Channel code="??STWH??????????" description="Steering Wheel Hub" version="1.0"/>
                <Channel code="??STWL??????????" description="Steering Wheel" version="1.0"/>
                <Channel code="??SUBF??????????" description="Subframe" version="1.0"/>
                <Channel code="??SUDO??????????" description="Suspension Dome" version="1.0"/>
                <Channel code="??SUHO??????????" description="Suspension Housing" version="1.0"/>
                <Channel code="??SUSM??????????" description="Suspension Mount" version="1.6"/>
                <Channel code="??SUUN??????????" description="Suspension Unit" version="1.6"/>
                <Channel code="??TAIG??????????" description="Tailgate" version="1.0"/>
                <Channel code="??TAIL??????????" description="Tail" version="1.5"/>
                <Channel code="??TBAT??????????" description="Traction Battery" version="1.6"/>
                <Channel code="??TOPT??????????" description="Top Tether" version="1.2"/>
                <Channel code="??TRAN??????????" description="Transmission" version="1.0"/>
                <Channel code="??TRCM??????????" description="Transmission Cross Member" version="1.6"/>
                <Channel code="??TUNN??????????" description="Tunnel" version="1.0"/>
                <Channel code="??VEHC??????????" description="Vehicle" version="1.0"/>
                <Channel code="??WARC??????????" description="Wheel Arch" version="1.2"/>
                <Channel code="??WHBC??????????" description="Wheel brake caliper" version="1.6.2.p1"/>
                <Channel code="??WHEL??????????" description="Wheel" version="1.0"/>
                <Channel code="??WIND??????????" description="Window" version="1.0"/>
            </Category>
            <Categor name="Calculation">
                <Channel code="??HICR??????????" description="Head Injury Criterion" remarks="based on AC" version="1.3"/>
                <Channel code="??BRIC??????????" description="BrIC - Brain Injury Criterion" remarks="just for CVC result value; based on AV" version="1.6.2.p1"/>
                <Channel code="??HACR??????????" description="Head Acceptability Criterion" version="1.3"/>
                <Channel code="??HPCR??????????" description="Head Protection Criterion" version="1.3"/>
                <Channel code="??HECD??????????" description="Head Contact Duration" version="1.3"/>
                <Channel code="??NICF??????????" description="NIC Load Duration" version="1.3"/>
                <Channel code="??NICR??????????" description="NIC, Rear Impact" version="1.3"/>
                <Channel code="??NIEF??????????" description="Neck Injury Criterion ENCAP" version="1.4"/>
                <Channel code="??NKMC??????????" description="Nkm Criterion" version="1.6"/>
                <Channel code="??NIJC??????????" description="Nij Criterion" version="1.3"/>
                <Channel code="??TMON??????????" description="Total Moment Neck" version="1.3"/>
                <Channel code="??VCCR??????????" description="Viscous Criterion" version="1.3"/>
                <Channel code="??VCAR??????????" description="Viscous Criterion Abdo. Rib" version="1.3"/>
                <Channel code="??THPC??????????" description="Thoracic Performance Criterion" version="1.4"/>
                <Channel code="??TTIN??????????" description="Thoracic Trauma Index" version="1.3"/>
                <Channel code="??THAC??????????" description="Thoracic Acceptability Crit." version="1.4"/>
                <Channel code="??CTIN??????????" description="Combined Thoracic Index" version="1.3"/>
                <Channel code="??THCC??????????" description="Thoracic Compression Criterion" version="1.4"/>
                <Channel code="??CHSI??????????" description="Severity Index Chest" version="1.3"/>
                <Channel code="??RDCR??????????" description="Rib Deflection Criterion" version="1.3"/>
                <Channel code="??RDAR??????????" description="Rib Deflection Crit. Abdomen" version="1.3"/>
                <Channel code="??APFC??????????" description="Abdominal Peak Force" version="1.4"/>
                <Channel code="??ADRA??????????" description="Abdominal Deflection Rate" version="1.6"/>
                <Channel code="??CDRA??????????" description="Chest Deflection Rate" version="1.6"/>
                <Channel code="??PSPF??????????" description="Pubic Symphysis Peak Force" version="1.3"/>
                <Channel code="??FFCE??????????" description="Femur Force Criterion" version="1.3"/>
                <Channel code="??FFCR??????????" description="Femur Force Criterion" version="1.3"/>
                <Channel code="??FACR??????????" description="Femur Acceptability Criterion" version="1.3"/>
                <Channel code="??TIIN??????????" description="Tibia Index" version="1.1"/>
                <Channel code="??TCFC??????????" description="Tibia Compression Criterion" version="1.3"/>
                <Channel code="??NCAP??????????" description="New Car Assessment Program" version="1.3"/>
                <Channel code="??AACP??????????" description="Average Acc. during Compression" version="1.3"/>
            </Categor>
            <Category name="Other">
                <Channel code="??0000??????????" description="Undefined" version="1.0"/>
                <Channel code="??1?????????????" description="Customer ID-Code XXX" version="1.0"/>
                <Channel code="??2?????????????" description="Laboratory ID-Code XXX" version="1.0"/>
                <Channel code="??ACTU??????????" description="Actuator" version="1.6"/>
                <Channel code="??DEFO??????????" description="Deformable Element" version="1.6.2.p2"/>
                <Channel code="??DTIM??????????" description="Time Step" remarks="numerical simulation" version="1.6.2.p1"/>
                <Channel code="??EHOU??????????" description="Hourglass Energy" remarks="numerical simulation" version="1.6.2.p1"/>
                <Channel code="??EINT??????????" description="Internal Energy" remarks="numerical simulation" version="1.6.2.p1"/>
                <Channel code="??EKIN??????????" description="Kinetic Energy" remarks="numerical simulation" version="1.6.2.p1"/>
                <Channel code="??ESLI??????????" description="Sliding Interface Energy" remarks="numerical simulation" version="1.6.2.p1"/>
                <Channel code="??ETOT??????????" description="Total Energy" remarks="numerical simulation" version="1.6.2.p1"/>
                <Channel code="??EXWO??????????" description="Total External Work" remarks="numerical simulation" version="1.6.2.p1"/>
                <Channel code="??FBAR??????????" description="Fixed Barrier" remarks="mandatory usage of Test Object 'B'" version="1.0"/>
                <Channel code="??GRND??????????" description="Ground, Sand Bed, Embankment" version="1.6.2.p2"/>
                <Channel code="??IMPA??????????" description="Impactor" remarks="intended for Video contour tracking" version="1.6.2.p1"/>
                <Channel code="??LOMA??????????" description="Load Cell Matrix" version="1.4"/>
                <Channel code="??LUGG??????????" description="Luggage" version="1.6.2"/>
                <Channel code="??MBAR??????????" description="Mobile Barrier" remarks="mandatory usage of Test Object 'M'" version="1.0"/>
                <Channel code="??MINC??????????" description="Mass Increase" remarks="numerical simulation" version="1.6.2.p1"/>
                <Channel code="??PLAF??????????" description="Platform" remarks="e.g. :platform of sled for pole test" version="1.6.2.p3"/>
                <Channel code="??POLE??????????" description="Pole" version="1.6"/>
                <Channel code="??RAMP??????????" description="Ramp" version="1.6.2.p2"/>
                <Channel code="??SENS??????????" description="Sensor" version="1.0"/>
                <Channel code="??SFAD??????????" description="Static Force Application Device" version="1.6"/>
                <Channel code="??SLED??????????" description="Sled" remarks="used for transducers directly mounted on the sled" version="1.0"/>
                <Channel code="??SUBJ??????????" description="Subject" remarks="mainly for Object Definition File Names" version="1.5"/>
                <Channel code="??TDCG??????????" description="Traction Device Center of Gravity" version="1.6.1"/>
                <Channel code="??TDLB??????????" description="Traction Device Lap Belt" remarks="used in ECE R14" version="1.6"/>
                <Channel code="??TDSB??????????" description="Traction Device Shoulder Belt" remarks="used in ECE R14" version="1.6"/>
                <Channel code="??TEST??????????" description="Test Signal" version="1.0"/>
                <Channel code="??TIRS??????????" description="Time Reference Signal" version="1.0"/>
                <Channel code="??ZERO??????????" description="Time Zero" version="1.0"/>
            </Category>
        </Element>
        <Element name="Fine Location 1">
            <Channel code="??????FB????????" description="Frontal Bone" remarks="temporary added for import of TH Codes" version="1.6.2.p1"/>
            <Channel code="??????MB????????" description="Mandibula" remarks="temporary added for import of TH Codes" version="1.6.2.p1"/>
            <Channel code="??????MX????????" description="Maxilla" remarks="temporary added for import of TH Codes" version="1.6.2.p1"/>
            <Channel code="??????00????????" description="Not defined" version="1.0"/>
            <Channel code="??????UP????????" description="Upper" version="1.0"/>
            <Channel code="??????AV????????" description="Average" remarks="Use 'AV' at FL1, if FL1 is '00'. If FL1 is already occupied, use 'AV' at FL2." version="1.6"/>
            <Channel code="??????BO????????" description="Bottom" remarks="also valid code for test object impact side descriptor" version="1.1"/>
            <Channel code="??????FR????????" description="Front" remarks="also valid code for test object impact side descriptor" version="1.0"/>
            <Channel code="??????IN????????" description="Inner" version="1.0"/>
            <Channel code="??????IS????????" description="Impact Sound Sensor" version="1.6"/>
            <Channel code="??????LE????????" description="Left" remarks="also valid code for test object impact side descriptor" version="1.0"/>
            <Channel code="??????LL????????" description="Left Lower" version="1.3"/>
            <Channel code="??????LO????????" description="Lower" version="1.0"/>
            <Channel code="??????LR????????" description="Left / Right" version="1.0"/>
            <Channel code="??????LU????????" description="Left Upper" version="1.3"/>
            <Channel code="??????MI????????" description="Middle" version="1.0"/>
            <Channel code="??????OU????????" description="Outer" version="1.0"/>
            <Channel code="??????RE????????" description="Rear" remarks="also valid code for test object impact side descriptor" version="1.0"/>
            <Channel code="??????RI????????" description="Right" version="1.0"/>
            <Channel code="??????RL????????" description="Right Lower" version="1.3"/>
            <Channel code="??????RU????????" description="Right Upper" version="1.3"/>
            <Channel code="??????TP????????" description="Top" remarks="also valid code for test object impact side descriptor" version="1.1"/>
            <Channel code="??????CG????????" description="Center of Gravity" version="1.0"/>
            <Channel code="??????CX????????" description="Center in X direction" version="1.1"/>
            <Channel code="??????CY????????" description="Center in Y direction" version="1.1"/>
            <Channel code="??????CZ????????" description="Center in Z direction" version="1.1"/>
            <Channel code="??????CU????????" description="Cumulative" version="1.3"/>
            <Channel code="??????SP????????" description="Single Peak" version="1.3"/>
            <Channel code="??????SU????????" description="Sum" remarks="Use 'SU' at FL1, if FL1 is '00'. If FL1 is already occupied, use 'SU' at FL2." version="1.3"/>
            <Channel code="??????EA????????" description="Extension Anterior Shear" remarks="Use with NKM-Criterion (ML = NKMC)" version="1.6"/>
            <Channel code="??????EP????????" description="Extension Posterior Shear" remarks="Use with NKMCriterion (ML = NKMC)" version="1.6"/>
            <Channel code="??????FA????????" description="Flexion Anterior Shear" remarks="Use with NKM-Criterion (ML = NKMC)" version="1.6"/>
            <Channel code="??????FP????????" description="Flexion Posterior Shear" remarks="Use with NKM-Criterion (ML = NKMC)" version="1.6"/>
            <Channel code="??????SM????????" description="SUFEHM Result" remarks="to be used for CVC of SUFEHM criterion" version="1.6.2"/>
            <Channel code="??????VM????????" description="Von Mises Stress (SUFEHM)" remarks="to be used for CVC of SUFEHM criterion" version="1.6.2"/>
            <Channel code="??????AD????????" description="Adult" version="1.3"/>
            <Channel code="??????CH????????" description="Child" version="1.3"/>
            <Channel code="??????CS????????" description="Crash Sensor" version="1.4"/>
            <Channel code="??????OR????????" description="Origin" version="1.6"/>
            <Channel code="??????PR????????" description="Pre Test" remarks="eg. for static measurement" version="1.6"/>
            <Channel code="??????RD????????" description="Redundant" version="1.0"/>
            <Channel code="??????LA????????" description="Left Anterior" remarks="intended for Human Models" version="1.6.2"/>
            <Channel code="??????LM????????" description="Left Middle" remarks="intended for Human Models" version="1.6.2"/>
            <Channel code="??????LP????????" description="Left" remarks="Posterior intended for Human Models" version="1.6.2.p2"/>
            <Channel code="??????RA????????" description="Right" remarks="Anterior intended for Human Models" version="1.6.2.p2"/>
            <Channel code="??????RM????????" description="Right" remarks="Middle intended for Human Models" version="1.6.2.p2"/>
            <Channel code="??????RP????????" description="Right" remarks="Posterior intended for Human Models" version="1.6.2.p2"/>
            <Channel code="??????IP????????" description="In Position" version="1.3"/>
            <Channel code="??????OP????????" description="Out of Position" version="1.3"/>
            <Channel code="??????AC????????" description="Anterior Cruciate Ligament" version="1.6"/>
            <Channel code="??????LC????????" description="Lateral Collateral Ligament" version="1.6"/>
            <Channel code="??????MC????????" description="Medial Collateral Ligament" version="1.6"/>
            <Channel code="??????PC????????" description="Posterior Cruciate Ligament" version="1.6"/>
            <Channel code="??????01????????" description="1." version="1.0"/>
            <Channel code="??????02????????" description="2." version="1.0"/>
            <Channel code="??????03????????" description="3." version="1.0"/>
            <Channel code="??????04????????" description="4." version="1.0"/>
            <Channel code="??????05????????" description="5." version="1.0"/>
            <Channel code="??????06????????" description="6." version="1.0"/>
            <Channel code="??????07????????" description="7." version="1.0"/>
            <Channel code="??????08????????" description="8." version="1.0"/>
            <Channel code="??????09????????" description="9." version="1.0"/>
            <Channel code="??????10????????" description="10." version="1.0"/>
            <Channel code="??????11????????" description="11." version="1.0"/>
            <Channel code="??????12????????" description="12." version="1.0"/>
            <Channel code="??????13????????" description="13." version="1.0"/>
            <Channel code="??????14????????" description="14." version="1.0"/>
            <Channel code="??????15????????" description="15." version="1.0"/>
            <Channel code="??????16????????" description="16." version="1.0"/>
            <Channel code="??????17????????" description="17." version="1.0"/>
            <Channel code="??????18????????" description="18." version="1.0"/>
            <Channel code="??????19????????" description="19." version="1.0"/>
            <Channel code="??????20????????" description="20." version="1.0"/>
            <Channel code="??????21????????" description="21." version="1.0"/>
            <Channel code="??????22????????" description="22." version="1.0"/>
            <Channel code="??????23????????" description="23." version="1.0"/>
            <Channel code="??????24????????" description="24." version="1.0"/>
            <Channel code="??????25????????" description="25." version="1.0"/>
            <Channel code="??????26????????" description="26." version="1.0"/>
            <Channel code="??????27????????" description="27." version="1.0"/>
            <Channel code="??????28????????" description="28." version="1.0"/>
            <Channel code="??????29????????" description="29." version="1.0"/>
            <Channel code="??????30????????" description="30." version="1.0"/>
            <Channel code="??????31????????" description="31." version="1.0"/>
            <Channel code="??????32????????" description="32." version="1.0"/>
            <Channel code="??????33????????" description="33." version="1.0"/>
            <Channel code="??????34????????" description="34." version="1.0"/>
            <Channel code="??????35????????" description="35." version="1.0"/>
            <Channel code="??????36????????" description="36." version="1.0"/>
            <Channel code="??????37????????" description="37." version="1.0"/>
            <Channel code="??????38????????" description="38." version="1.0"/>
            <Channel code="??????39????????" description="39." version="1.0"/>
            <Channel code="??????40????????" description="40." version="1.0"/>
            <Channel code="??????41????????" description="41." version="1.0"/>
            <Channel code="??????42????????" description="42." version="1.0"/>
            <Channel code="??????43????????" description="43." version="1.0"/>
            <Channel code="??????44????????" description="44." version="1.0"/>
            <Channel code="??????45????????" description="45." version="1.0"/>
            <Channel code="??????46????????" description="46." version="1.0"/>
            <Channel code="??????47????????" description="47." version="1.0"/>
            <Channel code="??????48????????" description="48." version="1.0"/>
            <Channel code="??????49????????" description="49." version="1.0"/>
            <Channel code="??????50????????" description="50." version="1.0"/>
            <Channel code="??????51????????" description="51." version="1.0"/>
            <Channel code="??????52????????" description="52." version="1.0"/>
            <Channel code="??????53????????" description="53." version="1.0"/>
            <Channel code="??????54????????" description="54." version="1.0"/>
            <Channel code="??????55????????" description="55." version="1.0"/>
            <Channel code="??????56????????" description="56." version="1.0"/>
            <Channel code="??????57????????" description="57." version="1.0"/>
            <Channel code="??????58????????" description="58." version="1.0"/>
            <Channel code="??????59????????" description="59." version="1.0"/>
            <Channel code="??????60????????" description="60." version="1.0"/>
            <Channel code="??????61????????" description="61." version="1.0"/>
            <Channel code="??????62????????" description="62." version="1.0"/>
            <Channel code="??????63????????" description="63." version="1.0"/>
            <Channel code="??????64????????" description="64." version="1.0"/>
            <Channel code="??????65????????" description="65." version="1.0"/>
            <Channel code="??????66????????" description="66." version="1.0"/>
            <Channel code="??????67????????" description="67." version="1.0"/>
            <Channel code="??????68????????" description="68." version="1.0"/>
            <Channel code="??????69????????" description="69." version="1.0"/>
            <Channel code="??????70????????" description="70." version="1.0"/>
            <Channel code="??????71????????" description="71." version="1.0"/>
            <Channel code="??????72????????" description="72." version="1.0"/>
            <Channel code="??????73????????" description="73." version="1.0"/>
            <Channel code="??????74????????" description="74." version="1.0"/>
            <Channel code="??????75????????" description="75." version="1.0"/>
            <Channel code="??????76????????" description="76." version="1.0"/>
            <Channel code="??????77????????" description="77." version="1.0"/>
            <Channel code="??????78????????" description="78." version="1.0"/>
            <Channel code="??????79????????" description="79." version="1.0"/>
            <Channel code="??????80????????" description="80." version="1.0"/>
            <Channel code="??????81????????" description="81." version="1.0"/>
            <Channel code="??????82????????" description="82." version="1.0"/>
            <Channel code="??????83????????" description="83." version="1.0"/>
            <Channel code="??????84????????" description="84." version="1.0"/>
            <Channel code="??????85????????" description="85." version="1.0"/>
            <Channel code="??????86????????" description="86." version="1.0"/>
            <Channel code="??????87????????" description="87." version="1.0"/>
            <Channel code="??????88????????" description="88." version="1.0"/>
            <Channel code="??????89????????" description="89." version="1.0"/>
            <Channel code="??????90????????" description="90." version="1.0"/>
            <Channel code="??????91????????" description="91." version="1.0"/>
            <Channel code="??????92????????" description="92." version="1.0"/>
            <Channel code="??????93????????" description="93." version="1.0"/>
            <Channel code="??????94????????" description="94." version="1.0"/>
            <Channel code="??????95????????" description="95." version="1.0"/>
            <Channel code="??????96????????" description="96." version="1.0"/>
            <Channel code="??????97????????" description="97." version="1.0"/>
            <Channel code="??????98????????" description="98." version="1.0"/>
            <Channel code="??????99????????" description="99." version="1.0"/>
        </Element>
        <Element name="Fine Location 2">
            <Channel code="????????00??????" description="Not defined" remarks="(eg. infinite HIC time interval)" version="1.0"/>
            <Channel code="????????BO??????" description="Bottom" version="1.1"/>
            <Channel code="????????FR??????" description="Front" version="1.0"/>
            <Channel code="????????IN??????" description="Inner" version="1.0"/>
            <Channel code="????????L1??????" description="Left Redundant" version="1.0"/>
            <Channel code="????????L2??????" description="Lower Redundant Now only used for Lower Redundant" version="1.0"/>
            <Channel code="????????LE??????" description="Left" version="1.0"/>
            <Channel code="????????LO??????" description="Lower" version="1.0"/>
            <Channel code="????????M1??????" description="Middle Redundant" version="1.5"/>
            <Channel code="????????MI??????" description="Middle" version="1.0"/>
            <Channel code="????????OU??????" description="Outer" version="1.0"/>
            <Channel code="????????R1??????" description="Right Redundant" version="1.0"/>
            <Channel code="????????RE??????" description="Rear" version="1.0"/>
            <Channel code="????????RI??????" description="Right" version="1.0"/>
            <Channel code="????????TP??????" description="Top" version="1.1"/>
            <Channel code="????????U1??????" description="Upper Redundant" version="1.0"/>
            <Channel code="????????UP??????" description="Upper" version="1.0"/>
            <Channel code="????????CG??????" description="Center of Gravity" version="1.0"/>
            <Channel code="????????CX??????" description="Center in X Direction" version="1.1"/>
            <Channel code="????????CY??????" description="Center in Y Direction" version="1.1"/>
            <Channel code="????????CZ??????" description="Center in Z Direction" version="1.1"/>
            <Channel code="????????AV??????" description="Average" remarks="'AV' is only used in FL2 if FL1 of base codes differs from '00'. Otherwise prefer to use 'AV' at FL1." version="1.0"/>
            <Channel code="????????DI??????" description="Difference" version="1.0"/>
            <Channel code="????????NE??????" description="Negative" version="1.3"/>
            <Channel code="????????PO??????" description="Positive" version="1.3"/>
            <Channel code="????????SF??????" description="Scale Factor" version="1.0"/>
            <Channel code="????????SU??????" description="Sum" remarks="Use 'SU' at FL1, if FL1 is '00'. If FL1 is already occupied, use 'SU' at FL2." version="1.0"/>
            <Channel code="?????????C??????" description="Xms Cumulative" remarks="like 5ms CLIP Value" version="1.3"/>
            <Channel code="?????????S??????" description="Xms Single Peak" remarks="like 5ms CLIP Value" version="1.3"/>
            <Channel code="????????3C??????" description="3ms CLIP Val. Cumulative" remarks="3ms CLIP Value" version="1.3"/>
            <Channel code="????????3S??????" description="3ms CLIP Val. Single Peak" remarks="3ms CLIP Value" version="1.3"/>
            <Channel code="????????CE??????" description="Compression Extension" version="1.0"/>
            <Channel code="????????CF??????" description="Compression Flexion" version="1.0"/>
            <Channel code="????????CO??????" description="Compression" version="1.3"/>
            <Channel code="????????DA??????" description="Duration of Loading Absolute" version="1.0"/>
            <Channel code="????????DN??????" description="Duration of Loading Negative" version="1.0"/>
            <Channel code="????????DP??????" description="Duration of Loading Positive" version="1.0"/>
            <Channel code="????????DU??????" description="Duration of Loading" version="1.0"/>
            <Channel code="????????FI??????" description="Fixed Interval (0...150ms)" remarks="Just used for BIORID and TRID Neck" version="1.3"/>
            <Channel code="????????FZ??????" description="Tibia Ratio from Axial Force (FZ)" version="1.6"/>
            <Channel code="????????HD??????" description="Head Performance Criterion" version="1.3"/>
            <Channel code="????????HS??????" description="High-Speed Sampling" version="1.6"/>
            <Channel code="????????LC??????" description="Limit Curve" version="1.0"/>
            <Channel code="????????MR??????" description="Tibia Ratio from Res. Bending Moment" version="1.6"/>
            <Channel code="????????RW??????" description="Raw data" version="1.6"/>
            <Channel code="????????SI??????" description="Selected Interval" remarks="just used for BIORID and TRID Neck" version="1.3"/>
            <Channel code="????????TE??????" description="Tension Extension" version="1.0"/>
            <Channel code="????????TF??????" description="Tension Flexion" version="1.0"/>
            <Channel code="????????TN??????" description="Tension" version="1.3"/>
            <Channel code="????????TO??????" description="Total Moment" version="1.0"/>
            <Channel code="????????XC??????" description="Xg Exceedence Time Cumulative" remarks="Should be used for HEAD, CHST (exceed. level needed in ISO-code?)" version="1.6"/>
            <Channel code="????????XS??????" description="Xg Exceedence Time Single Peak" remarks="Should be used for HEAD, CHST (exceed. level needed in ISO-code?)" version="1.6"/>
            <Channel code="????????OR??????" description="Origin" version="1.6"/>
            <Channel code="????????PR??????" description="Pre Test" remarks="eg. for static measurement" version="1.6.2.p1"/>
            <Channel code="????????SQ??????" description="Squib" remarks="to be used with separate airbag timer firing" version="1.6"/>
            <Channel code="????????RD??????" description="Redundant" version="1.0"/>
            <Channel code="????????01??????" description="1." version="1.0"/>
            <Channel code="????????02??????" description="2." version="1.0"/>
            <Channel code="????????03??????" description="3." remarks="also used in combination with CHST DS with H3,HF,Y7,… to mark cubic chest deflection channel" version="1.0"/>
            <Channel code="????????04??????" description="4." version="1.0"/>
            <Channel code="????????05??????" description="5." version="1.0"/>
            <Channel code="????????06??????" description="6." version="1.0"/>
            <Channel code="????????07??????" description="7." version="1.0"/>
            <Channel code="????????08??????" description="8." version="1.0"/>
            <Channel code="????????09??????" description="9." version="1.0"/>
            <Channel code="????????10??????" description="10." version="1.0"/>
            <Channel code="????????11??????" description="11." version="1.0"/>
            <Channel code="????????12??????" description="12." version="1.0"/>
            <Channel code="????????13??????" description="13." version="1.0"/>
            <Channel code="????????14??????" description="14." version="1.0"/>
            <Channel code="????????15??????" description="15." remarks="eg. 15ms HIC time interval" version="1.0"/>
            <Channel code="????????16??????" description="16." version="1.0"/>
            <Channel code="????????17??????" description="17." version="1.0"/>
            <Channel code="????????18??????" description="18." version="1.0"/>
            <Channel code="????????19??????" description="19." version="1.0"/>
            <Channel code="????????20??????" description="20." version="1.0"/>
            <Channel code="????????21??????" description="21." version="1.0"/>
            <Channel code="????????22??????" description="22." version="1.0"/>
            <Channel code="????????23??????" description="23." version="1.0"/>
            <Channel code="????????24??????" description="24." version="1.0"/>
            <Channel code="????????25??????" description="25." version="1.0"/>
            <Channel code="????????26??????" description="26." version="1.0"/>
            <Channel code="????????27??????" description="27." version="1.0"/>
            <Channel code="????????28??????" description="28." version="1.0"/>
            <Channel code="????????29??????" description="29." version="1.0"/>
            <Channel code="????????30??????" description="30." version="1.0"/>
            <Channel code="????????31??????" description="31." version="1.0"/>
            <Channel code="????????32??????" description="32." version="1.0"/>
            <Channel code="????????33??????" description="33." version="1.0"/>
            <Channel code="????????34??????" description="34." version="1.0"/>
            <Channel code="????????35??????" description="35." version="1.0"/>
            <Channel code="????????36??????" description="36." remarks="eg. 36ms HIC time interval" version="1.0"/>
            <Channel code="????????37??????" description="37." version="1.0"/>
            <Channel code="????????38??????" description="38." version="1.0"/>
            <Channel code="????????39??????" description="39." version="1.0"/>
            <Channel code="????????40??????" description="40." version="1.0"/>
            <Channel code="????????41??????" description="41." version="1.0"/>
            <Channel code="????????42??????" description="42." version="1.0"/>
            <Channel code="????????43??????" description="43." version="1.0"/>
            <Channel code="????????44??????" description="44." version="1.0"/>
            <Channel code="????????45??????" description="45." version="1.0"/>
            <Channel code="????????46??????" description="46." version="1.0"/>
            <Channel code="????????47??????" description="47." version="1.0"/>
            <Channel code="????????48??????" description="48." version="1.0"/>
            <Channel code="????????49??????" description="49." version="1.0"/>
            <Channel code="????????50??????" description="50." version="1.0"/>
            <Channel code="????????51??????" description="51." version="1.0"/>
            <Channel code="????????52??????" description="52." version="1.0"/>
            <Channel code="????????53??????" description="53." version="1.0"/>
            <Channel code="????????54??????" description="54." version="1.0"/>
            <Channel code="????????55??????" description="55." version="1.0"/>
            <Channel code="????????56??????" description="56." version="1.0"/>
            <Channel code="????????57??????" description="57." version="1.0"/>
            <Channel code="????????58??????" description="58." version="1.0"/>
            <Channel code="????????59??????" description="59." version="1.0"/>
            <Channel code="????????60??????" description="60." version="1.0"/>
            <Channel code="????????61??????" description="61." version="1.0"/>
            <Channel code="????????62??????" description="62." version="1.0"/>
            <Channel code="????????63??????" description="63." version="1.0"/>
            <Channel code="????????64??????" description="64." version="1.0"/>
            <Channel code="????????65??????" description="65." version="1.0"/>
            <Channel code="????????66??????" description="66." version="1.0"/>
            <Channel code="????????67??????" description="67." version="1.0"/>
            <Channel code="????????68??????" description="68." version="1.0"/>
            <Channel code="????????69??????" description="69." version="1.0"/>
            <Channel code="????????70??????" description="70." version="1.0"/>
            <Channel code="????????71??????" description="71." version="1.0"/>
            <Channel code="????????72??????" description="72." version="1.0"/>
            <Channel code="????????73??????" description="73." version="1.0"/>
            <Channel code="????????74??????" description="74." version="1.0"/>
            <Channel code="????????75??????" description="75." version="1.0"/>
            <Channel code="????????76??????" description="76." version="1.0"/>
            <Channel code="????????77??????" description="77." version="1.0"/>
            <Channel code="????????78??????" description="78." version="1.0"/>
            <Channel code="????????79??????" description="79." version="1.0"/>
            <Channel code="????????80??????" description="80." version="1.0"/>
            <Channel code="????????81??????" description="81." version="1.0"/>
            <Channel code="????????82??????" description="82." version="1.0"/>
            <Channel code="????????83??????" description="83." version="1.0"/>
            <Channel code="????????84??????" description="84." version="1.0"/>
            <Channel code="????????85??????" description="85." version="1.0"/>
            <Channel code="????????86??????" description="86." version="1.0"/>
            <Channel code="????????87??????" description="87." version="1.0"/>
            <Channel code="????????88??????" description="88." version="1.0"/>
            <Channel code="????????89??????" description="89." version="1.0"/>
            <Channel code="????????90??????" description="90." version="1.0"/>
            <Channel code="????????91??????" description="91." version="1.0"/>
            <Channel code="????????92??????" description="92." version="1.0"/>
            <Channel code="????????93??????" description="93." version="1.0"/>
            <Channel code="????????94??????" description="94." version="1.0"/>
            <Channel code="????????95??????" description="95." version="1.0"/>
            <Channel code="????????96??????" description="96." version="1.0"/>
            <Channel code="????????97??????" description="97." version="1.0"/>
            <Channel code="????????98??????" description="98." version="1.0"/>
            <Channel code="????????99??????" description="99." version="1.0"/>
        </Element>
        <Element name="Fine Location 3">
            <Channel code="??????????00????" description="Not defined" version="1.0"/>
            <Channel code="??????????BO????" description="Bottom" version="1.1"/>
            <Channel code="??????????FR????" description="Front" version="1.0"/>
            <Channel code="??????????IN????" description="Inner" version="1.0"/>
            <Channel code="??????????LE????" description="Left" version="1.0"/>
            <Channel code="??????????LO????" description="Lower" version="1.0"/>
            <Channel code="??????????MI????" description="Middle" version="1.0"/>
            <Channel code="??????????OU????" description="Outer" version="1.0"/>
            <Channel code="??????????RE????" description="Rear" version="1.0"/>
            <Channel code="??????????RI????" description="Right" version="1.0"/>
            <Channel code="??????????TP????" description="Top" version="1.1"/>
            <Channel code="??????????UP????" description="Upper" version="1.0"/>
            <Channel code="??????????CG????" description="Center of Gravity" version="1.0"/>
            <Channel code="??????????CX????" description="Center in X direction" version="1.1"/>
            <Channel code="??????????CY????" description="Center in Y direction" version="1.1"/>
            <Channel code="??????????CZ????" description="Center in Z direction" version="1.1"/>
            <Channel code="??????????PO????" description="Post Test" remarks="eg. for static measurement" version="1.5"/>
            <Channel code="??????????PR????" description="Pre Test" remarks="eg. for static measurement" version="1.5"/>
            <Channel code="??????????A3????" description="Airbagdummy 3 year old" version="1.0"/>
            <Channel code="??????????BP????" description="Back Pan" remarks="used for seat back testing" version="1.6.1"/>
            <Channel code="??????????BR????" description="BioRID" version="1.0"/>
            <Channel code="??????????BS????" description="BioSID Dummy" version="1.0"/>
            <Channel code="??????????E1????" description="EuroSID-1 Dummy" version="1.0"/>
            <Channel code="??????????E2????" description="ES-2 Dummy" version="1.2"/>
            <Channel code="??????????ER????" description="ES-2 Dummy with Rib Extension" version="1.5"/>
            <Channel code="??????????H2????" description="Hybrid II Mid-Sized Male Dummy" version="1.0"/>
            <Channel code="??????????H3????" description="Hybrid III Mid-Sized Adult Male Dummy" version="1.0"/>
            <Channel code="??????????HA????" description="FAA 50th Dummy" version="1.6.2.p1"/>
            <Channel code="??????????HB????" description="FAA 95th Dummy" version="1.6.2.p1"/>
            <Channel code="??????????HF????" description="Hybrid III Small Adult Female" version="1.0"/>
            <Channel code="??????????HH????" description="Head Hemisphere" remarks="like head hemisphere for FMVSS 202a, ECE R17, ECE R21, GTR 7 (165mm diameter, mass of 6,8kg)" version="1.6"/>
            <Channel code="??????????HM????" description="Hybrid III Large Adult Male Dummy" version="1.0"/>
            <Channel code="??????????MA????" description="Large omnidirectional Child 10 year" remarks="LODC" version="1.6.2.p3"/>
            <Channel code="??????????MD????" description="Motorcycle Dummy" version="1.0"/>
            <Channel code="??????????P0????" description="Newborn Dummy" version="1.0"/>
            <Channel code="??????????P1????" description="TNO P 3/4 year old Dummy" version="1.0"/>
            <Channel code="??????????P2????" description="TNO P 1 1/2 year old Dummy" version="1.0"/>
            <Channel code="??????????P3????" description="TNO P 3 year old Dummy" version="1.0"/>
            <Channel code="??????????P4????" description="TNO P 6 year old Dummy" version="1.0"/>
            <Channel code="??????????P5????" description="TNO P 10 year old Dummy" version="1.0"/>
            <Channel code="??????????Q0????" description="Q0 Dummy" version="1.5"/>
            <Channel code="??????????Q1????" description="Q1 Dummy" version="1.5"/>
            <Channel code="??????????Q2????" description="Q1 1/2 Dummy" version="1.5"/>
            <Channel code="??????????Q3????" description="Q3 Dummy" version="1.5"/>
            <Channel code="??????????Q4????" description="Q3 Dummy Side Impact" version="1.5"/>
            <Channel code="??????????Q6????" description="Q6 Dummy" version="1.5"/>
            <Channel code="??????????QA????" description="Q10 Dummy" version="1.5"/>
            <Channel code="??????????QB????" description="Q10 Dummy (EuroNCAP)" version="1.6.2.p3"/>
            <Channel code="??????????R2????" description="RID 2" version="1.3"/>
            <Channel code="??????????S2????" description="SID IIs Dummy" version="1.0"/>
            <Channel code="??????????SH????" description="SID H3 Dummy" version="1.0"/>
            <Channel code="??????????SI????" description="SID (US) Dummy" version="1.0"/>
            <Channel code="??????????T1????" description="TNO-10 Dummy (Standard 75 kg)" version="1.0"/>
            <Channel code="??????????T3????" description="THOR with H3 Legs" version="1.6.2.p2"/>
            <Channel code="??????????T5????" description="THOR Small Female with HF Legs" remarks="place holder; dummy not existing in 2017" version="1.6.2.p2"/>
            <Channel code="??????????T9????" description="THOR Large Adult Male with HM Legs" remarks="place holder; dummy not existing in 2017" version="1.6.2.p2"/>
            <Channel code="??????????TF????" description="THOR Small Size Female Dummy" version="1.5"/>
            <Channel code="??????????TH????" description="THOR Dummy" version="1.0"/>
            <Channel code="??????????TM????" description="THOR Large Adult Male Dummy" remarks="place holder; dummy not existing in 2017" version="1.6.2.p2"/>
            <Channel code="??????????TV????" description="THOR 50% AV" remarks="dummy for autonomous driving" version="1.6.2"/>
            <Channel code="??????????TW????" description="THOR 5% AV" remarks="dummy for autonomous driving" version="1.6.2"/>
            <Channel code="??????????WA????" description="WIAMan 50th Male" remarks="For Military use: Warrior Injury Assessment Manikin" version="1.6.2.p3"/>
            <Channel code="??????????WB????" description="WIAMan 5th Female" remarks="For Military use: Warrior Injury Assessment Manikin" version="1.6.2.p3"/>
            <Channel code="??????????WC????" description="WIAMan 95th Male" remarks="For Military use: Warrior Injury Assessment Manikin" version="1.6.2.p3"/>
            <Channel code="??????????WF????" description="WorldSID Small Adult Female Dummy" version="1.5"/>
            <Channel code="??????????WS????" description="WorldSID Dummy" version="1.5"/>
            <Channel code="??????????Y1????" description="Crabi 6 month old Dummy" version="1.0"/>
            <Channel code="??????????Y2????" description="Crabi 12 month old Dummy" version="1.0"/>
            <Channel code="??????????Y3????" description="Crabi 18 month old Dummy" version="1.0"/>
            <Channel code="??????????Y4????" description="Child 3 year old Dummy (Part 572 C)" version="1.2"/>
            <Channel code="??????????Y5????" description="Child 6 year old Dummy (Part 572 I)" version="1.2"/>
            <Channel code="??????????Y6????" description="Hybrid III 3 year old Dummy (Part 572 P)" version="1.2"/>
            <Channel code="??????????Y7????" description="Hybrid III 6 year old Dummy (Part 572 N)" version="1.2"/>
            <Channel code="??????????Y8????" description="Cami 3 month old Dummy" version="1.0"/>
            <Channel code="??????????Y9????" description="Cami 6 month old Dummy" version="1.0"/>
            <Channel code="??????????YA????" description="Hybrid III 10 year old Dummy" version="1.5"/>
            <Channel code="??????????YW????" description="Hybrid III 6 year old Dummy weighted (Part 572 S)" version="1.6.2.p2"/>
            <Channel code="??????????BB????" description="Body Block" version="1.0"/>
            <Channel code="??????????FH????" description="Free Motion Headform" version="1.4"/>
            <Channel code="??????????HE????" description="Headform" version="1.5"/>
            <Channel code="??????????PA????" description="Adult Headform" version="1.5"/>
            <Channel code="??????????PB????" description="ACEA Headform" version="1.5"/>
            <Channel code="??????????PC????" description="Child Headform" version="1.4"/>
            <Channel code="??????????PJ????" description="JARI Headform" version="1.5"/>
            <Channel code="??????????PM????" description="aPLI Legform Impactor" version="1.6.2.p3"/>
            <Channel code="??????????PS????" description="JARI Child Headform" version="1.4"/>
            <Channel code="??????????PF????" description="Flexible Legform Impactor" version="1.5"/>
            <Channel code="??????????PL????" description="Legform Pedestrian Impactor" version="1.5"/>
            <Channel code="??????????PU????" description="Upper Leg Pedestrian Impactor" version="1.4"/>
            <Channel code="??????????V6????" description="Virtual Child 6 year old" remarks="Human Models" version="1.6.2.p2"/>
            <Channel code="??????????VA????" description="Virtual Child 10 year old" remarks="Human Models" version="1.6.2.p2"/>
            <Channel code="??????????VF????" description="5th Percentile Human Female" remarks="Human Models" version="1.6.2.p2"/>
            <Channel code="??????????VH????" description="50th Percentile Human Male" remarks="Human Models" version="1.6.2.p2"/>
            <Channel code="??????????VM????" description="95th Percentile Human Male" remarks="Human Models" version="1.6.2.p2"/>
            <Channel code="??????????B1????" description="belt at retractor" version="1.0"/>
            <Channel code="??????????B2????" description="belt below belt loop" version="1.0"/>
            <Channel code="??????????B3????" description="belt at upper diagonal belt" version="1.0"/>
            <Channel code="??????????B4????" description="belt at lower diagonal belt" version="1.0"/>
            <Channel code="??????????B5????" description="belt at lap belt inside" version="1.0"/>
            <Channel code="??????????B6????" description="belt at lap belt outside" version="1.0"/>
            <Channel code="??????????AF????" description="Frontal Airbag" version="1.4"/>
            <Channel code="??????????AH????" description="Head Airbag" version="1.4"/>
            <Channel code="??????????AI????" description="Interaction Airbag" version="1.6.2.p2"/>
            <Channel code="??????????AP????" description="Pedestrian Airbag" version="1.4"/>
            <Channel code="??????????AR????" description="Rear Airbag" version="1.4"/>
            <Channel code="??????????AS????" description="Side Airbag" version="1.4"/>
            <Channel code="??????????GF????" description="Frontal Airbag Generator" version="1.4"/>
            <Channel code="??????????GH????" description="Head Airbag Generator" version="1.4"/>
            <Channel code="??????????GI????" description="Interaction Airbag Generator" version="1.6.2.p2"/>
            <Channel code="??????????GP????" description="Passenger Airbag Generator" version="1.4"/>
            <Channel code="??????????GR????" description="Rear Airbag Generator" version="1.4"/>
            <Channel code="??????????GS????" description="Side Airbag Generator" version="1.4"/>
            <Channel code="??????????RD????" description="Redundant" version="1.4"/>
            <Channel code="??????????DA????" description="Side Impact AEMDB Barrier Face" remarks="Barrier face, use in combination with M0DEFO" version="1.6.2.p1"/>
            <Channel code="??????????DB????" description="Frontal Oblique Impact (NHTSA) Barrier Face" remarks="Barrier face, use in combination with M0DEFO" version="1.6.2.p1"/>
            <Channel code="??????????DE????" description="Side Impact EuroNCAP Barrier Face" remarks="Barrier face, use in combination with M0DEFO" version="1.6.2.p1"/>
            <Channel code="??????????DI????" description="Side Impact IIHS Barrier Face" remarks="Barrier face, use in combination with M0DEFO" version="1.6.2.p1"/>
            <Channel code="??????????DM????" description="Frontal MPDB ADAC Barrier Face" remarks="Barrier face, use in combination with M0DEFO" version="1.6.2.p1"/>
            <Channel code="??????????DN????" description="Side Impact NHTSA Barrier Face" remarks="Barrier face, use in combination with M0DEFO" version="1.6.2.p1"/>
            <Channel code="??????????DO????" description="Frontal Offset Barrier Face" remarks="Barrier face, use in combination with B0DEFO" version="1.6.2.p1"/>
            <Channel code="??????????01????" description="1." version="1.0"/>
            <Channel code="??????????02????" description="2." version="1.0"/>
            <Channel code="??????????03????" description="3." version="1.0"/>
            <Channel code="??????????04????" description="4." version="1.0"/>
            <Channel code="??????????05????" description="5." version="1.0"/>
            <Channel code="??????????06????" description="6." version="1.0"/>
            <Channel code="??????????07????" description="7." version="1.0"/>
            <Channel code="??????????08????" description="8." version="1.0"/>
            <Channel code="??????????09????" description="9." version="1.0"/>
            <Channel code="??????????10????" description="10." version="1.0"/>
            <Channel code="??????????11????" description="11." version="1.0"/>
            <Channel code="??????????12????" description="12." version="1.0"/>
            <Channel code="??????????13????" description="13." version="1.0"/>
            <Channel code="??????????14????" description="14." version="1.0"/>
            <Channel code="??????????15????" description="15." version="1.0"/>
            <Channel code="??????????16????" description="16." version="1.0"/>
            <Channel code="??????????17????" description="17." version="1.0"/>
            <Channel code="??????????18????" description="18." version="1.0"/>
            <Channel code="??????????19????" description="19." version="1.0"/>
            <Channel code="??????????20????" description="20." version="1.0"/>
            <Channel code="??????????21????" description="21." version="1.0"/>
            <Channel code="??????????22????" description="22." version="1.0"/>
            <Channel code="??????????23????" description="23." version="1.0"/>
            <Channel code="??????????24????" description="24." version="1.0"/>
            <Channel code="??????????25????" description="25." version="1.0"/>
            <Channel code="??????????26????" description="26." version="1.0"/>
            <Channel code="??????????27????" description="27." version="1.0"/>
            <Channel code="??????????28????" description="28." version="1.0"/>
            <Channel code="??????????29????" description="29." version="1.0"/>
            <Channel code="??????????30????" description="30." version="1.0"/>
            <Channel code="??????????31????" description="31." version="1.0"/>
            <Channel code="??????????32????" description="32." version="1.0"/>
            <Channel code="??????????33????" description="33." version="1.0"/>
            <Channel code="??????????34????" description="34." version="1.0"/>
            <Channel code="??????????35????" description="35." version="1.0"/>
            <Channel code="??????????36????" description="36." version="1.0"/>
            <Channel code="??????????37????" description="37." version="1.0"/>
            <Channel code="??????????38????" description="38." version="1.0"/>
            <Channel code="??????????39????" description="39." version="1.0"/>
            <Channel code="??????????40????" description="40." version="1.0"/>
            <Channel code="??????????41????" description="41." version="1.0"/>
            <Channel code="??????????42????" description="42." version="1.0"/>
            <Channel code="??????????43????" description="43." version="1.0"/>
            <Channel code="??????????44????" description="44." version="1.0"/>
            <Channel code="??????????45????" description="45." version="1.0"/>
            <Channel code="??????????46????" description="46." version="1.0"/>
            <Channel code="??????????47????" description="47." version="1.0"/>
            <Channel code="??????????48????" description="48." version="1.0"/>
            <Channel code="??????????49????" description="49." version="1.0"/>
            <Channel code="??????????50????" description="50." version="1.0"/>
            <Channel code="??????????51????" description="51." version="1.0"/>
            <Channel code="??????????52????" description="52." version="1.0"/>
            <Channel code="??????????53????" description="53." version="1.0"/>
            <Channel code="??????????54????" description="54." version="1.0"/>
            <Channel code="??????????55????" description="55." version="1.0"/>
            <Channel code="??????????56????" description="56." version="1.0"/>
            <Channel code="??????????57????" description="57." version="1.0"/>
            <Channel code="??????????58????" description="58." version="1.0"/>
            <Channel code="??????????59????" description="59." version="1.0"/>
            <Channel code="??????????60????" description="60." version="1.0"/>
            <Channel code="??????????61????" description="61." version="1.0"/>
            <Channel code="??????????62????" description="62." version="1.0"/>
            <Channel code="??????????63????" description="63." version="1.0"/>
            <Channel code="??????????64????" description="64." version="1.0"/>
            <Channel code="??????????65????" description="65." version="1.0"/>
            <Channel code="??????????66????" description="66." version="1.0"/>
            <Channel code="??????????67????" description="67." version="1.0"/>
            <Channel code="??????????68????" description="68." version="1.0"/>
            <Channel code="??????????69????" description="69." version="1.0"/>
            <Channel code="??????????70????" description="70." version="1.0"/>
            <Channel code="??????????71????" description="71." version="1.0"/>
            <Channel code="??????????72????" description="72." version="1.0"/>
            <Channel code="??????????73????" description="73." version="1.0"/>
            <Channel code="??????????74????" description="74." version="1.0"/>
            <Channel code="??????????75????" description="75." version="1.0"/>
            <Channel code="??????????76????" description="76." version="1.0"/>
            <Channel code="??????????77????" description="77." version="1.0"/>
            <Channel code="??????????78????" description="78." version="1.0"/>
            <Channel code="??????????79????" description="79." version="1.0"/>
            <Channel code="??????????80????" description="80." version="1.0"/>
            <Channel code="??????????81????" description="81." version="1.0"/>
            <Channel code="??????????82????" description="82." version="1.0"/>
            <Channel code="??????????83????" description="83." version="1.0"/>
            <Channel code="??????????84????" description="84." version="1.0"/>
            <Channel code="??????????85????" description="85." version="1.0"/>
            <Channel code="??????????86????" description="86." version="1.0"/>
            <Channel code="??????????87????" description="87." version="1.0"/>
            <Channel code="??????????88????" description="88." version="1.0"/>
            <Channel code="??????????89????" description="89." version="1.0"/>
            <Channel code="??????????90????" description="90." version="1.0"/>
            <Channel code="??????????91????" description="91." version="1.0"/>
            <Channel code="??????????92????" description="92." version="1.0"/>
            <Channel code="??????????93????" description="93." version="1.0"/>
            <Channel code="??????????94????" description="94." version="1.0"/>
            <Channel code="??????????95????" description="95." version="1.0"/>
            <Channel code="??????????96????" description="96." version="1.0"/>
            <Channel code="??????????97????" description="97." version="1.0"/>
            <Channel code="??????????98????" description="98." version="1.0"/>
            <Channel code="??????????99????" description="99." version="1.0"/>
        </Element>
        <Element name="Physical Dimension">
            <Channel code="????????????00??" description="Others" default_unit="1" version="1.0"/>
            <Channel code="????????????1???" description="Laboratory Specific Physical Dimension" default_unit="?" version="1.5"/>
            <Channel code="????????????2???" description="Customer Specific Physical Dimension" default_unit="?" version="1.5"/>
            <Channel code="????????????AA??" description="Angular Acceleration" default_unit="rad/(s*s)" version="1.0"/>
            <Channel code="????????????AC??" description="Acceleration" default_unit="m/(s*s)" version="1.0"/>
            <Channel code="????????????AD??" description="Auditory Damage Units (ADU)" default_unit="dB" remarks="According German AK3 (08.10.2002) has ADU no Unit" version="1.0"/>
            <Channel code="????????????AN??" description="Angle" default_unit="rad" version="1.0"/>
            <Channel code="????????????AR??" description="Area" default_unit="m*m" version="1.6.1"/>
            <Channel code="????????????AV??" description="Angular Velocity" default_unit="rad/s" version="1.0"/>
            <Channel code="????????????CH??" description="Charge" default_unit="C" version="1.0"/>
            <Channel code="????????????CU??" description="Current" default_unit="A" version="1.0"/>
            <Channel code="????????????DC??" description="Distance" default_unit="m" remarks="Distance between two points in space" version="1.0"/>
            <Channel code="????????????DS??" description="Displacement" default_unit="m" remarks="Displacement/movement of one point in space" version="1.0"/>
            <Channel code="????????????DV??" description="Displacement, integrated from Velocity" default_unit="m" version="1.5"/>
            <Channel code="????????????EC??" description="Electrical Capacity" default_unit="F = A*s/V" version="1.6.2"/>
            <Channel code="????????????EN??" description="Energy" default_unit="J" version="1.0"/>
            <Channel code="????????????EV??" description="Event" default_unit="1" version="1.0"/>
            <Channel code="????????????FO??" description="Force" default_unit="N" version="1.0"/>
            <Channel code="????????????FR??" description="Frequency" default_unit="Hz" version="1.0"/>
            <Channel code="????????????HU??" description="Humidity" default_unit="%" version="1.0"/>
            <Channel code="????????????IL??" description="Illuminance" default_unit="lx" version="1.5"/>
            <Channel code="????????????IM??" description="Impulse" default_unit="kg*m/s" version="1.0"/>
            <Channel code="????????????JE??" description="Jerk" default_unit="m/(s*s*s)" version="1.6.2.p1"/>
            <Channel code="????????????LE??" description="Lever Arm" default_unit="m" version="1.0"/>
            <Channel code="????????????LF??" description="Luminous Flux" default_unit="lm" version="1.5"/>
            <Channel code="????????????LI??" description="Luminous Intensity" default_unit="cd" version="1.5"/>
            <Channel code="????????????LU??" description="Luminance" default_unit="cd/(m*m)" version="1.5"/>
            <Channel code="????????????MA??" description="Mass" default_unit="kg" version="1.0"/>
            <Channel code="????????????MF??" description="Mass Flow Rate" default_unit="kg/s" version="1.6.2.p3"/>
            <Channel code="????????????MO??" description="Moment" default_unit="Nm" version="1.0"/>
            <Channel code="????????????PO??" description="Power" default_unit="W" version="1.0"/>
            <Channel code="????????????PR??" description="Pressure" default_unit="Pa" version="1.0"/>
            <Channel code="????????????QU??" description="Quaternion" default_unit="1" version="1.6"/>
            <Channel code="????????????RE??" description="Resistance" default_unit="V/A" version="1.0"/>
            <Channel code="????????????SA??" description="Solid angle (steradiant)" default_unit="sr" version="1.5"/>
            <Channel code="????????????SE??" description="Sensitivity" default_unit="(Unit) / (Unit)" version="1.0"/>
            <Channel code="????????????SP??" description="Peak Sound Pressure Level (SPL)" default_unit="dB" version="1.0"/>
            <Channel code="????????????SR??" description="Mechanical Stress" default_unit="Pa" version="1.0"/>
            <Channel code="????????????ST??" description="Strain" default_unit="m/m" version="1.0"/>
            <Channel code="????????????TE??" description="Temperature" default_unit="K" version="1.0"/>
            <Channel code="????????????TI??" description="Time" default_unit="s" version="1.0"/>
            <Channel code="????????????VA??" description="Velocity, Integr. from Acc." default_unit="m/s" version="1.4"/>
            <Channel code="????????????VD??" description="Velocity, Diff. from Displ." default_unit="m/s" version="1.4"/>
            <Channel code="????????????VE??" description="Velocity" default_unit="m/s" version="1.0"/>
            <Channel code="????????????VF??" description="Volume Flow Rate" default_unit="m*m*m/s" version="1.6.2.p3"/>
            <Channel code="????????????VO??" description="Voltage" default_unit="V" version="1.0"/>
            <Channel code="????????????VU??" description="Volume" default_unit="m*m*m" version="1.0"/>
        </Element>
        <Element name="Direction">
            <Channel code="??????????????0?" description="Undefined/other" version="1.0"/>
            <Channel code="??????????????R?" description="Resultant" version="1.0"/>
            <Channel code="??????????????X?" description="Longitudinal" version="1.0"/>
            <Channel code="??????????????Y?" description="Lateral" version="1.0"/>
            <Channel code="??????????????Z?" description="Vertical" version="1.0"/>
            <Channel code="??????????????1?" description="Longitudinal" remarks="divergent to SAE J211 Sign convention" version="1.2"/>
            <Channel code="??????????????2?" description="Lateral" remarks="divergent to SAE J211 Sign convention" version="1.2"/>
            <Channel code="??????????????3?" description="Vertical" remarks="divergent to SAE J211 Sign convention" version="1.2"/>
        </Element>
        <Element name="Filter Class">
            <Channel code="???????????????0" description="Unfiltered" version="1.0"/>
            <Channel code="???????????????1" description="FIR 100" remarks="NHTSA Filter Code" version="1.0"/>
            <Channel code="???????????????2" description="Combined A and B" remarks="NIJ according to SAE J1727" version="1.0"/>
            <Channel code="???????????????3" description="Combined B and C" remarks="CTI" version="1.0"/>
            <Channel code="???????????????A" description="CFC 1000" remarks="ISO 6487* / SAE J211:MAR95" version="1.0"/>
            <Channel code="???????????????B" description="CFC 600" remarks="ISO 6487* / SAE J211:MAR95" version="1.0"/>
            <Channel code="???????????????C" description="CFC 180" remarks="ISO 6487* / SAE J211:MAR95" version="1.0"/>
            <Channel code="???????????????D" description="CFC 60" remarks="ISO 6487* / SAE J211:MAR95" version="1.0"/>
            <Channel code="???????????????E" description="CFC 1000" remarks="ISO 6487:1987 / SAE J211:OCT88" version="1.0"/>
            <Channel code="???????????????F" description="CFC 600" remarks="ISO 6487:1987 / SAE J211:OCT88" version="1.0"/>
            <Channel code="???????????????G" description="CFC 180" remarks="ISO 6487:1987 / SAE J211:OCT88" version="1.0"/>
            <Channel code="???????????????H" description="CFC 60" remarks="ISO 6487:1987 / SAE J211:OCT88" version="1.0"/>
            <Channel code="???????????????L" description="CFC 20" remarks="intended for angular velocity" version="1.6.2"/>
            <Channel code="???????????????P" description="Prefiltered &gt; CFC 1000" remarks="Described in 'Test Channel File'" version="1.0"/>
            <Channel code="???????????????Q" description="Prefiltered &lt; CFC 60" remarks="Described in 'Test Channel File'" version="1.0"/>
            <Channel code="???????????????S" description="Special Filter" remarks="See Channel Header" version="1.5"/>
            <Channel code="???????????????V" description="Data from film(video) analysis" version="1.3"/>
            <Channel code="???????????????X" description="Without (Constant Channel)" version="1.0"/>
        </Element>
    </Codification>
</Channel_Codes>